Workbook

Sheet Cotizador 3D
B2: Cotizador de impresiones
B3: Marca de filamento | C3: Mexico Makers/SUNLU | D3: *opcional
B4: Material: | C4: PLA | D4: *opcional
B5: Gramos consumidos: | C5: 315 | D5: Gramos
B6: Tiempo de impresion : | C6: 13 | D6: Horas
B7: Post-procesado: | C7: 0 | D7: *Pintura, lijado, acabados,
B8: Costo de embalaje: | C8: 0 | D8: * En caso de ser necesario, caja, bolsa, etc.
B9: Costo total de fabricacion: | C9: ='Desglose de calculo '!C21 -> 418.61111
B10: Margen: | C10: 0.3 | D10: porcentaje de ganancia
B11: Total: | C11: ='Desglose de calculo '!C24 -> 598.01587
B12: Ganancia: | C12: =C11-C9 -> 179.40476

Sheet Desglose de calculo 
B2: Desglose de cálculos
B3: Marca de filamento | C3: ='Cotizador 3D'!C3 -> Mexico Makers/SUNLU
B4: Material: | C4: ='Cotizador 3D'!C4 -> PLA
B6: Gramos consumidos: | C6: ='Cotizador 3D'!C5 -> 315
B7: Costo de filamento por gramo | C7: ='Configuracion del cotizador'!C6 -> 0.35
B8: Costo total del material: | C8: =C7*C6 -> 110.25 | D8: Calculo: Gramos consumidos X Costo de filamento por gramo
B10: Tiempo de impresion : | C10: ='Cotizador 3D'!C6 -> 13
B11: Costo total por hora : | C11: ='Configuracion del cotizador'!C38 -> 20.5
B12: Total por horas de impresion | C12: =C10*C11 -> 266.5 | D12: Calculo: Tiempro de impresion X Costo total por hora
B14: Costo de fabricación: | C14: =C8+C12 -> 376.75 | D14: Calculo: Total por horas de impresion + Costo Total material
B15: Margen de protección : | C15: 0.1 | D15: *margen de proteccion en caso de problemas
B16: Costo de fabricacion con margen: | C16: =C14/(1-C15) -> 418.61111 | D16: Calculo: costo de fabricación / ( 1- margen de protección )
B18: Post-procesado: | C18: ='Cotizador 3D'!C7 -> 0
B19: Costo de embalaje: | C19: ='Cotizador 3D'!C8 -> 0
B21: Costo total de fabricacion: | C21: =C16+C18+C19 -> 418.61111 | D21: Calculo: Costo de fabricacion con margen + Post-procesado + Costo de embalaje
B23: Margen de Ganancia: | C23: ='Cotizador 3D'!C10 -> 0.3 | D23: Porcentaje de ganancia
B24: Total: | C24: =C21/(1-C23) -> 598.01587 | D24: Calculo: Costo total de fabricacion / (1 - Margen de ganancia)
C26: ='Cotizador 3D'!C13

Sheet Configuracion del cotizador
B2: Configuracion del cotizador
B3: Parametros del Filamento
B4: Costo del filamento: | C4: 350
B5: Gramos de filamento por carrete: | C5: 1000 | D5: *por defecto 1,000gr
B6: Costo de filamento por gramo | C6: =C4/C5 -> 0.35 | D6: Calculo: Costo de filamento / Gramos de filamento por carrete
B9: Parametros de la impresora
B10: Costo de las impresoras: | C10: 12000 | D10: *Valor sumado de las impresoras
B11: Costo mensual de mantenimiento : | C11: 400 | D11: *Costo total de mantenimiento
B13: Amortización de inversión
B14: Meses de retorno de inversion de la maquina : | C14: 24
B15: Dias laborales en el mes: | C15: 24
B16: Horas minimas de impresion | C16: 10 | D16: * Tiempo de impresion esperado por dia SUMANDO TODAS LAS IMPRESORAS
B17: Total de hrs de amortizacion: | C17: =C16*C15*C14 -> 5760 | D17: Calculo: Dias laborales en el mes * Horas minimas de impresion *meses de retorno de inversión
B18: Total de horas al mes : | C18: =C16*C15 -> 240 | D18: Calculo: Dias laborales en el mes * Horas minimas de impresion
B20: Gastos de operación
B21: Consumo electrico mensual: | C21: 120 | D21: *Valor del recibo o cunsumo parcial electrico
B22: Cosumo electrico por hora: | C22: =C21/C18 -> 0.5 | D22: Calculo: Cosumo electrico mensual / Total de hrs al mes
B24: Internet mensual : | C24: 200
B25: Gasto internet por hora: | C25: =C24/C18 -> 0.83333333 | D25: Calculo: Internet mensual / Total de horas al mes
B27: Gastos publicitarios Mensuales: | C27: 200
B28: Gasto publisitario por hora: | C28: =C27/C18 -> 0.83333333 | D28: Calculo: Publicidad mensual / Total de horas al mes
B30: Gastos extras mensuales fijos : | C30: 3500 | D30: *Gastos como renta, agua, empleados etc.
B31: Gastos por hora: | C31: =C30/C18 -> 14.583333 | D31: Calculo: Gastos extras mensuales / Total de horas al mes
B33: Costes por hora
B35: Gastos mensuales totales por hora | C35: =C22+C25+C28+C31 -> 16.75 | D35: Calculo: Suma de todos los valores por hora de la seccion de gastos de operación
B36: Costo de maquina por hr: | C36: =C10/C17 -> 2.0833333 | D36: Calculo: Costo de las impresoras / Total de horas de amortizacion
B37: Costo de mantenimiento por hr: | C37: =C11/C18 -> 1.6666667 | D37: Calculo: Costo mensual de mantenimiento / Total de horas al mes
B38: Costo total por hora : | C38: =C35+C36+C37 -> 20.5 | D38: Calculo: Gastos mensuales totales por hora + costo de maquina por hr + costo de mantenimiento por hr
